esrally/__init__.py
esrally/_version.py
esrally/actor.py
esrally/config.py
esrally/exceptions.py
esrally/log.py
esrally/metrics.py
esrally/min-es-version.txt
esrally/paths.py
esrally/racecontrol.py
esrally/rally.py
esrally/rallyd.py
esrally/reporter.py
esrally/telemetry.py
esrally/time.py
esrally/types.py
esrally/version.py
esrally/client/__init__.py
esrally/client/asynchronous.py
esrally/client/common.py
esrally/client/context.py
esrally/client/factory.py
esrally/client/synchronous.py
esrally/driver/__init__.py
esrally/driver/driver.py
esrally/driver/runner.py
esrally/driver/scheduler.py
esrally/mechanic/__init__.py
esrally/mechanic/cluster.py
esrally/mechanic/java_resolver.py
esrally/mechanic/launcher.py
esrally/mechanic/mechanic.py
esrally/mechanic/provisioner.py
esrally/mechanic/supplier.py
esrally/mechanic/team.py
esrally/resources/annotation-template.json
esrally/resources/challenges.json.j2
esrally/resources/docker-compose.yml.j2
esrally/resources/logging.json
esrally/resources/metrics-template.json
esrally/resources/operations.json.j2
esrally/resources/races-template.json
esrally/resources/rally.ini
esrally/resources/results-template.json
esrally/resources/track-schema.json
esrally/resources/track.json.j2
esrally/track/__init__.py
esrally/track/loader.py
esrally/track/params.py
esrally/track/track.py
esrally/tracker/__init__.py
esrally/tracker/corpus.py
esrally/tracker/index.py
esrally/tracker/tracker.py
esrally/utils/__init__.py
esrally/utils/cases.py
esrally/utils/collections.py
esrally/utils/console.py
esrally/utils/convert.py
esrally/utils/git.py
esrally/utils/io.py
esrally/utils/jvm.py
esrally/utils/modules.py
esrally/utils/net.py
esrally/utils/opts.py
esrally/utils/pretty.py
esrally/utils/process.py
esrally/utils/repo.py
esrally/utils/serverless.py
esrally/utils/sysstats.py
esrally/utils/versions.py
esrally-2.12.0.dist-info/METADATA
esrally-2.12.0.dist-info/WHEEL
esrally-2.12.0.dist-info/entry_points.txt
esrally-2.12.0.dist-info/licenses/AUTHORS
esrally-2.12.0.dist-info/licenses/LICENSE
esrally-2.12.0.dist-info/licenses/NOTICE
esrally-2.12.0.dist-info/RECORD
