Metadata-Version: 2.4
Name: esrally
Version: 2.12.0
Summary: Macrobenchmarking framework for Elasticsearch
Project-URL: Changelog, https://github.com/elastic/rally/blob/master/CHANGELOG.md
Project-URL: Documentation, https://esrally.readthedocs.io/
Project-URL: Code, https://github.com/elastic/rally
Project-URL: Issue tracker, https://github.com/elastic/rally/issues
Author-email: Daniel Mitterdorfer <daniel.mitterdorfer@gmail.com>
License: Apache License 2.0
License-File: AUTHORS
License-File: LICENSE
License-File: NOTICE
Classifier: Development Status :: 5 - Production/Stable
Classifier: Intended Audience :: Developers
Classifier: License :: OSI Approved :: Apache Software License
Classifier: Operating System :: MacOS :: MacOS X
Classifier: Operating System :: POSIX
Classifier: Programming Language :: Python
Classifier: Programming Language :: Python :: 3
Classifier: Programming Language :: Python :: 3 :: Only
Classifier: Programming Language :: Python :: 3.9
Classifier: Programming Language :: Python :: 3.10
Classifier: Programming Language :: Python :: 3.11
Classifier: Programming Language :: Python :: 3.12
Classifier: Topic :: System :: Benchmark
Requires-Python: >=3.9
Requires-Dist: aiohttp==3.10.11
Requires-Dist: certifi
Requires-Dist: docker==6.0.0
Requires-Dist: ecs-logging==2.2.0
Requires-Dist: elastic-transport==8.4.1
Requires-Dist: elasticsearch[async]==8.6.1
Requires-Dist: google-auth==2.38.0
Requires-Dist: google-resumable-media[requests]==1.1.0
Requires-Dist: ijson==2.6.1
Requires-Dist: jinja2==3.1.5
Requires-Dist: jsonschema==3.1.1
Requires-Dist: markupsafe==2.0.1
Requires-Dist: psutil==5.9.4
Requires-Dist: py-cpuinfo==7.0.0
Requires-Dist: python-json-logger==2.0.7
Requires-Dist: requests<2.32.0
Requires-Dist: tabulate==0.8.9
Requires-Dist: thespian==4.0.1
Requires-Dist: typing-extensions==4.12.2
Requires-Dist: urllib3==1.26.19
Requires-Dist: yappi==1.5.1
Requires-Dist: zstandard==0.21.0
Provides-Extra: develop
Requires-Dist: black==24.10.0; extra == 'develop'
Requires-Dist: boto3-stubs==1.26.125; extra == 'develop'
Requires-Dist: boto3==1.34.68; extra == 'develop'
Requires-Dist: furo==2022.06.21; extra == 'develop'
Requires-Dist: github3-py==3.2.0; extra == 'develop'
Requires-Dist: gitpython==3.1.30; extra == 'develop'
Requires-Dist: mypy==1.15.0; extra == 'develop'
Requires-Dist: nox==2024.3.2; extra == 'develop'
Requires-Dist: pre-commit==2.20.0; extra == 'develop'
Requires-Dist: pylint==3.1.0; extra == 'develop'
Requires-Dist: pytest-asyncio==0.19.0; extra == 'develop'
Requires-Dist: pytest-benchmark==3.4.1; extra == 'develop'
Requires-Dist: pytest-httpserver==1.0.5; extra == 'develop'
Requires-Dist: pytest==7.1.2; extra == 'develop'
Requires-Dist: sphinx==5.1.1; extra == 'develop'
Requires-Dist: tox==3.25.0; extra == 'develop'
Requires-Dist: trustme==0.9.0; extra == 'develop'
Requires-Dist: types-jsonschema==3.2.0; extra == 'develop'
Requires-Dist: types-psutil==5.9.4; extra == 'develop'
Requires-Dist: types-requests<2.32.0; extra == 'develop'
Requires-Dist: types-tabulate==0.8.9; extra == 'develop'
Requires-Dist: types-urllib3==1.26.19; extra == 'develop'
Requires-Dist: ujson; extra == 'develop'
Provides-Extra: s3
Requires-Dist: boto3==1.34.68; extra == 's3'
